{"is_source_file": true, "format": "TypeScript", "description": "Utility helper functions for Recipe Explorer, including slugification of strings, formatting time durations into human-readable labels, and combining CSS class names.", "external_files": [], "external_methods": [], "published": ["slugify", "formatTime", "classNames"], "classes": [], "methods": [{"name": "export function slugify(input: string): string { slugify", "description": "Converts a string into a URL-safe, lowercase slug by removing accents, replacing non-alphanumeric characters with hyphens, and trimming hyphens from the ends.", "scope": "", "scopeKind": ""}, {"name": "export function formatTime(totalMinutes?: number): string { formatTime", "description": "Converts a number of minutes into a human-readable string like \"1h 20m\" or \"35m\"; returns '\u2014' if input is invalid or non-positive.", "scope": "", "scopeKind": ""}, {"name": "export function classNames(...classes: Array<string | false | null | undefined>): string { classNames", "description": "Joins an array of class name strings, filtering out falsey values, into a single space-separated string.", "scope": "", "scopeKind": ""}], "calls": ["input.toLowerCase()", "input.normalize('NFKD')", "String.prototype.replace", "Math.floor", "totalMinutes % 60", "classes.filter"], "search-terms": ["slugify", "formatTime", "classNames", "helper functions", "utility functions", "timestamp formatting", "string normalization"], "state": 2, "file_id": 14, "knowledge_revision": 36, "git_revision": "", "ctags": [{"_type": "tag", "name": "classNames", "path": "/home/kavia/workspace/code-generation/recipe-explorer-209096-209126/frontend_app/src/lib/utils.ts", "pattern": "/^export function classNames(...classes: Array<string | false | null | undefined>): string {$/", "language": "TypeScript", "kind": "function"}, {"_type": "tag", "name": "formatTime", "path": "/home/kavia/workspace/code-generation/recipe-explorer-209096-209126/frontend_app/src/lib/utils.ts", "pattern": "/^export function formatTime(totalMinutes?: number): string {$/", "language": "TypeScript", "kind": "function"}, {"_type": "tag", "name": "h", "path": "/home/kavia/workspace/code-generation/recipe-explorer-209096-209126/frontend_app/src/lib/utils.ts", "pattern": "/^  const h = Math.floor(totalMinutes \\/ 60);$/", "language": "TypeScript", "kind": "constant", "scope": "formatTime", "scopeKind": "function"}, {"_type": "tag", "name": "m", "path": "/home/kavia/workspace/code-generation/recipe-explorer-209096-209126/frontend_app/src/lib/utils.ts", "pattern": "/^  const m = totalMinutes % 60;$/", "language": "TypeScript", "kind": "constant", "scope": "formatTime", "scopeKind": "function"}, {"_type": "tag", "name": "slugify", "path": "/home/kavia/workspace/code-generation/recipe-explorer-209096-209126/frontend_app/src/lib/utils.ts", "pattern": "/^export function slugify(input: string): string {$/", "language": "TypeScript", "kind": "function"}], "hash": "ff991c3c4b42e6e51a21ae5b4fc94622", "format-version": 4, "code-base-name": "frontend_app", "filename": "frontend_app/src/lib/utils.ts", "revision_history": [{"36": ""}]}